sanic_jsonrpc/__init__.py
sanic_jsonrpc/_context.py
sanic_jsonrpc/errors.py
sanic_jsonrpc/loggers.py
sanic_jsonrpc/notifier.py
sanic_jsonrpc/types.py
sanic_jsonrpc/_middleware/__init__.py
sanic_jsonrpc/_middleware/directions.py
sanic_jsonrpc/_middleware/objects.py
sanic_jsonrpc/_middleware/predicate.py
sanic_jsonrpc/_middleware/predicates.py
sanic_jsonrpc/_middleware/transports.py
sanic_jsonrpc/jsonrpc/__init__.py
sanic_jsonrpc/jsonrpc/_basejsonrpc.py
sanic_jsonrpc/jsonrpc/sanicjsonrpc.py
sanic_jsonrpc/models/__init__.py
sanic_jsonrpc/models/_jsonrpc.py
sanic_jsonrpc/models/error.py
sanic_jsonrpc/models/notification.py
sanic_jsonrpc/models/request.py
sanic_jsonrpc/models/response.py
sanic_jsonrpc-0.4.0.dist-info/LICENSE
sanic_jsonrpc-0.4.0.dist-info/METADATA
sanic_jsonrpc-0.4.0.dist-info/WHEEL
sanic_jsonrpc-0.4.0.dist-info/top_level.txt
sanic_jsonrpc-0.4.0.dist-info/RECORD
