Metadata-Version: 2.1
Name: sanic-jsonrpc
Version: 0.4.0
Summary: JSON-RPC 2.0 support for Sanic over HTTP and WebSocket
Home-page: https://github.com/mon4ter/sanic-jsonrpc
Author: Dmitry Galkin
Author-email: mon4ter@gmail.com
License: MIT
Platform: UNKNOWN
Classifier: Development Status :: 4 - Beta
Classifier: Programming Language :: Python :: 3.5
Classifier: Programming Language :: Python :: 3.6
Classifier: Programming Language :: Python :: 3.7
Classifier: Programming Language :: Python :: 3.8
Classifier: Programming Language :: Python :: 3.9
Classifier: License :: OSI Approved :: MIT License
Classifier: Operating System :: OS Independent
License-File: LICENSE
Requires-Dist: fashionable (~=0.12.2)
Requires-Dist: sanic (~=19.3.1) ; python_version < "3.6"
Requires-Dist: ujson (~=3.2.0) ; python_version < "3.6"
Requires-Dist: websockets (~=6.0) ; python_version < "3.6"
Requires-Dist: sanic (~=20.12.3) ; python_version == "3.6"
Requires-Dist: websockets (~=8.1) ; python_version == "3.6"
Requires-Dist: ujson (~=4.1.0) ; python_version >= "3.6"
Requires-Dist: sanic (~=21.6.2) ; python_version >= "3.7"
Requires-Dist: websockets (~=9.1) ; python_version >= "3.7"
